testlink/__init__.py
testlink/proxiedtransport2.py
testlink/proxiedtransport3.py
testlink/testgenreporter.py
testlink/testlinkapi.py
testlink/testlinkapigeneric.py
testlink/testlinkargs.py
testlink/testlinkdecorators.py
testlink/testlinkerrors.py
testlink/testlinkhelper.py
testlink/testreporter.py
testlink/version.py
TestLink_API_Python_client_fix-0.8.2.dev141.dist-info/LICENSE-2.0.txt
TestLink_API_Python_client_fix-0.8.2.dev141.dist-info/METADATA
TestLink_API_Python_client_fix-0.8.2.dev141.dist-info/WHEEL
TestLink_API_Python_client_fix-0.8.2.dev141.dist-info/top_level.txt
TestLink_API_Python_client_fix-0.8.2.dev141.dist-info/RECORD
