Metadata-Version: 2.1
Name: TestLink-API-Python-client-fix
Version: 0.8.2.dev141
Summary: Python XML-RPC client for TestLink 1.9.20-fixed_c88e348ce
Home-page: https://github.com/lczub/TestLink-API-Python-client
Author: James Stock, Olivier Renault, Luiko Czub, TestLink-API-Python-client developers
Author-email: orenault@gmail.com, Luiko.Czub@Liegkat-Archiv.de
License: Apache 2.0
Keywords: testing,testlink,xml-rpc,testautomation
Platform: any
Classifier: Development Status :: 5 - Production/Stable
Classifier: License :: OSI Approved :: Apache Software License
Classifier: Operating System :: OS Independent
Classifier: Programming Language :: Python :: 2.7
Classifier: Programming Language :: Python :: 3.6
Classifier: Programming Language :: Python :: 3.7
Classifier: Topic :: Software Development :: Testing
Classifier: Topic :: Software Development :: Libraries :: Python Modules
License-File: LICENSE-2.0.txt
